odoo/addons/maintenance_plan/README.rst
odoo/addons/maintenance_plan/__init__.py
odoo/addons/maintenance_plan/__manifest__.py
odoo/addons/maintenance_plan/hooks.py
odoo/addons/maintenance_plan/data/demo_maintenance_plan.xml
odoo/addons/maintenance_plan/i18n/es.po
odoo/addons/maintenance_plan/i18n/gl.po
odoo/addons/maintenance_plan/i18n/it.po
odoo/addons/maintenance_plan/i18n/maintenance_plan.pot
odoo/addons/maintenance_plan/migrations/11.0.2.0.0/post-migration.py
odoo/addons/maintenance_plan/models/__init__.py
odoo/addons/maintenance_plan/models/maintenance_equipment.py
odoo/addons/maintenance_plan/models/maintenance_kind.py
odoo/addons/maintenance_plan/models/maintenance_plan.py
odoo/addons/maintenance_plan/models/maintenance_request.py
odoo/addons/maintenance_plan/readme/CONTRIBUTORS.rst
odoo/addons/maintenance_plan/readme/DESCRIPTION.rst
odoo/addons/maintenance_plan/readme/INSTALL.rst
odoo/addons/maintenance_plan/readme/USAGE.rst
odoo/addons/maintenance_plan/security/ir.model.access.csv
odoo/addons/maintenance_plan/static/description/icon.png
odoo/addons/maintenance_plan/static/description/index.html
odoo/addons/maintenance_plan/tests/__init__.py
odoo/addons/maintenance_plan/tests/test_maintenance_plan.py
odoo/addons/maintenance_plan/views/maintenance_equipment_views.xml
odoo/addons/maintenance_plan/views/maintenance_kind_views.xml
odoo/addons/maintenance_plan/views/maintenance_plan_views.xml
odoo11_addon_maintenance_plan-11.0.2.4.1.dist-info/METADATA
odoo11_addon_maintenance_plan-11.0.2.4.1.dist-info/WHEEL
odoo11_addon_maintenance_plan-11.0.2.4.1.dist-info/top_level.txt
odoo11_addon_maintenance_plan-11.0.2.4.1.dist-info/RECORD
